MyPhotos/__init__.py
MyPhotos/config/selfconfig.py
MyPhotos/config/yamlconfig.py
MyPhotos/data/fbasic.py
MyPhotos/data/hash.py
MyPhotos/data/xls.py
MyPhotos-0.0.2.dist-info/METADATA
MyPhotos-0.0.2.dist-info/WHEEL
MyPhotos-0.0.2.dist-info/top_level.txt
MyPhotos-0.0.2.dist-info/RECORD
