Metadata-Version: 2.1
Name: MyPhotos
Version: 0.0.2
Summary: Archive photos for quick search.
Home-page: https://github.com/zoumingzhe/MyPhotos
Author: Zou Mingzhe
Author-email: zoumingzhe@qq.com
License: MIT
Platform: any
Classifier: Development Status :: 5 - Production/Stable
Classifier: Intended Audience :: Developers
Classifier: Intended Audience :: End Users/Desktop
Classifier: License :: OSI Approved :: MIT License
Classifier: Natural Language :: Chinese (Simplified)
Classifier: Operating System :: Microsoft :: Windows
Classifier: Programming Language :: Python
Classifier: Programming Language :: Python :: 3
Classifier: Programming Language :: Python :: 3.6
Classifier: Topic :: Software Development :: Libraries
Classifier: Topic :: Software Development :: Libraries :: Python Modules
Requires-Dist: xlrd
Requires-Dist: xlwt
